ipay_python/__init__.py
ipay_python/exceptions.py
ipay_python/ipay.py
ipay_python-0.1.1.dist-info/METADATA
ipay_python-0.1.1.dist-info/WHEEL
ipay_python-0.1.1.dist-info/licenses/LICENSE
ipay_python-0.1.1.dist-info/RECORD
