Metadata-Version: 2.1
Name: ipay_python
Version: 0.1.1
Summary: Low-level wrapper over Bank of Georgia's payment gateway ipay.
Project-URL: Homepage, https://github.com/gigamarr/ipay_python
Project-URL: Bug Tracker, https://github.com/gigamarr/ipay_python/issues
Author-email: gigamarr <marsagishviligig@gmail.com>
License-File: LICENSE
Classifier: License :: OSI Approved :: MIT License
Classifier: Operating System :: OS Independent
Classifier: Programming Language :: Python :: 3
Requires-Python: >=3.7
